pyIcingaFramework/__init__.py
pyIcingaFramework/cache.py
pyIcingaFramework/check.py
pyIcingaFramework/exceptions.py
pyIcingaFramework/ic2check.py
pyIcingaFramework/utils.py
pyIcingaFramework/checks/__init__.py
pyIcingaFramework/checks/test/__init__.py
pyIcingaFramework/checks/test/testcheck.py
pyIcingaFramework-0.0.10.dist-info/METADATA
pyIcingaFramework-0.0.10.dist-info/WHEEL
pyIcingaFramework-0.0.10.dist-info/entry_points.txt
pyIcingaFramework-0.0.10.dist-info/top_level.txt
pyIcingaFramework-0.0.10.dist-info/RECORD
