Metadata-Version: 2.1
Name: pyIcingaFramework
Version: 0.0.10
Summary: Icinga2 Check Framework library
Author: Paul Denning
Keywords: icinga2,nagios
Classifier: Intended Audience :: Developers
Classifier: Programming Language :: Python :: 3
